{"cameraMode":{"drawMode":0,"name":"Shaded","section":"Shading Mode"},"sceneLighting":true,"audioPlay":false,"sceneViewState":{"m_AlwaysRefresh":false,"showFog":true,"showSkybox":true,"showFlares":true,"showImageEffects":true,"showParticleSystems":true,"showVisualEffectGraphs":true,"m_FxEnabled":true},"in2DMode":false,"pivot":{"x":7.854053974151611,"y":0.2867316007614136,"z":5.594597339630127},"rotation":{"x":0.13911473751068116,"y":0.3955848813056946,"z":-0.06086381897330284,"w":0.9059664011001587},"size":7.234009265899658,"orthographic":false}